TESSify/__init__.py
tessify-0.4.2.dist-info/licenses/LICENSE.txt
tessify-0.4.2.dist-info/METADATA
tessify-0.4.2.dist-info/WHEEL
tessify-0.4.2.dist-info/top_level.txt
tessify-0.4.2.dist-info/RECORD
