Metadata-Version: 2.4
Name: TESSify
Version: 0.4.2
Summary: A Python package for helping with detecting exoplanet transit dips in TESS light curves.
Home-page: https://github.com/arpit290/TESSify
Author: Arpit Bishnoi
Author-email: bishnoiarpit29@gmail.com
Classifier: Programming Language :: Python :: 3
Classifier: License :: OSI Approved :: MIT License
Classifier: Operating System :: OS Independent
Requires-Python: >=3.7
License-File: LICENSE.txt
Requires-Dist: lightkurve
Requires-Dist: numpy
Requires-Dist: matplotlib
Requires-Dist: pillow
Dynamic: author
Dynamic: author-email
Dynamic: classifier
Dynamic: description
Dynamic: description-content-type
Dynamic: home-page
Dynamic: license-file
Dynamic: requires-dist
Dynamic: requires-python
Dynamic: summary
